remotsylib3/__init__.py
remotsylib3/api_async.py
remotsylib3-0.0.1.dist-info/LICENSE.txt
remotsylib3-0.0.1.dist-info/METADATA
remotsylib3-0.0.1.dist-info/WHEEL
remotsylib3-0.0.1.dist-info/top_level.txt
remotsylib3-0.0.1.dist-info/RECORD
