Metadata-Version: 2.1
Name: remotsylib3
Version: 0.0.1
Summary: A Remotsy lib for use the Restfull API
Home-page: https://github.com/jorgecis/remotsylib3
Author: Jasmit Tarang
Author-email: jaytarang92@gmail.com
License: UNKNOWN
Keywords: Remotsy infrared remote control smarthome
Platform: UNKNOWN
Classifier: Development Status :: 4 - Beta
Classifier: Intended Audience :: Developers
Classifier: Topic :: Software Development :: Build Tools
Classifier: License :: OSI Approved :: MIT License
Classifier: Programming Language :: Python :: 3
Classifier: Programming Language :: Python :: 3.4
Classifier: Programming Language :: Python :: 3.5
Classifier: Programming Language :: Python :: 3.6
Classifier: Programming Language :: Python :: 3.7
